localstack_utils/__init__.py
localstack_utils/container.py
localstack_utils/localstack.py
localstack_utils/localstack_docker_configuration.py
localstack_utils/localstack_logger.py
localstack_utils-1.0.1.dist-info/METADATA
localstack_utils-1.0.1.dist-info/WHEEL
localstack_utils-1.0.1.dist-info/top_level.txt
localstack_utils-1.0.1.dist-info/RECORD
