Metadata-Version: 2.1
Name: localstack-utils
Version: 1.0.1
Summary: Utils for testing with LocalStack
Home-page: https://github.com/localstack/localstack-python-utils
Author: Cristopher Pinzon
Author-email: cristopher.pinzon@localstack.cloud
License: Apache License 2.0
Classifier: Development Status :: 5 - Production/Stable
Classifier: License :: OSI Approved :: Apache Software License
Classifier: Operating System :: OS Independent
Classifier: Programming Language :: Python :: 3
Classifier: Programming Language :: Python :: 3.8
Classifier: Programming Language :: Python :: 3.9
Classifier: Programming Language :: Python :: 3.10
Classifier: Programming Language :: Python :: 3.11
Classifier: Topic :: Software Development :: Libraries
Classifier: Topic :: Utilities
Requires-Dist: docker >=6.1.1
Requires-Dist: nose >=1.3.7
Requires-Dist: nose-timer >=0.7.5
Provides-Extra: dev
Requires-Dist: boto3 >=1.26.121 ; extra == 'dev'
Requires-Dist: pytest >=7.4.0 ; extra == 'dev'
Requires-Dist: black ==23.10.0 ; extra == 'dev'
Requires-Dist: ruff ==0.1.0 ; extra == 'dev'
